tap_singer_jsonl/__init__.py
tap_singer_jsonl/utils.py
tap_singer_jsonl-0.1.0.dist-info/WHEEL
tap_singer_jsonl-0.1.0.dist-info/METADATA
tap_singer_jsonl-0.1.0.dist-info/entry_points.txt
tap_singer_jsonl-0.1.0.dist-info/RECORD
